CHANGES.txt
CONTRIBUTORS.txt
README.txt
buildout.cfg
setup.py
collective/__init__.py
collective.recipe.seleniumrc.egg-info/PKG-INFO
collective.recipe.seleniumrc.egg-info/SOURCES.txt
collective.recipe.seleniumrc.egg-info/dependency_links.txt
collective.recipe.seleniumrc.egg-info/entry_points.txt
collective.recipe.seleniumrc.egg-info/namespace_packages.txt
collective.recipe.seleniumrc.egg-info/requires.txt
collective.recipe.seleniumrc.egg-info/top_level.txt
collective/recipe/__init__.py
collective/recipe/seleniumrc/__init__.py
collective/recipe/seleniumrc/defaults.cfg
collective/recipe/seleniumrc/seleniumrc_ctl.in