Metadata-Version: 1.0
Name: collective.recipe.seleniumrc
Version: 0.6.1.1
Summary: zc.buildout recipe for installing the Selenium RC distribution.
Home-page: http://svn.plone.org/svn/collective/buildout/collective.recipe.seleniumrc
Author: Jordan Baker
Author-email: jbb@scryent.com
License: ZPL 2.1
Keywords: buildout recipe
Platform: UNKNOWN
Classifier: Framework :: Buildout
Classifier: Topic :: Software Development :: Build Tools
